[
    {
        "id": "animate-objects",
        "name": "Animate Objects",
        "level": "5",
        "school": "Transmutation",
        "duration": "1 minute",
        "range": "120 feet",
        "area_type": "None",
        "dtype": "None",
        "condition": "None",
        "ritual": false,
        "concentration": true,
        "srd": true
    },
    {
        "id": "bigbys-hand",
        "name": "Bigbys Hand",
        "level": "5",
        "school": "Evocation",
        "duration": "1 minute",
        "range": "120 feet",
        "area_type": "None",
        "dtype": "Multiple",
        "condition": "Grappled",
        "ritual": false,
        "concentration": true,
        "srd": true
    },
    {
        "id": "circle-of-power",
        "name": "Circle of Power",
        "level": "5",
        "school": "Abjuration",
        "duration": "10 minutes",
        "range": "Self",
        "area_type": "sphere (30)",
        "dtype": "None",
        "condition": "None",
        "ritual": false,
        "concentration": true,
        "srd": false
    },
    {
        "id": "cloudkill",
        "name": "Cloudkill",
        "level": "5",
        "school": "Conjuration",
        "duration": "10 minutes",
        "range": "120 feet",
        "area_type": "sphere (20)",
        "dtype": "Poison",
        "condition": "None",
        "ritual": false,
        "concentration": true,
        "srd": true
    },
    {
        "id": "cone-of-cold",
        "name": "Cone of Cold",
        "level": "5",
        "school": "Evocation",
        "duration": "Instantaneous",
        "range": "Self",
        "area_type": "cone (60)",
        "dtype": "Cold",
        "condition": "None",
        "ritual": false,
        "concentration": false,
        "srd": true
    },
    {
        "id": "conjure-elemental",
        "name": "Conjure Elemental",
        "level": "5",
        "school": "Conjuration",
        "duration": "10 minutes",
        "range": "60 feet",
        "area_type": "None",
        "dtype": "Multiple",
        "condition": "Restrained",
        "ritual": false,
        "concentration": true,
        "srd": true
    },
    {
        "id": "contact-other-plane",
        "name": "Contact Other Plane",
        "level": "5",
        "school": "Divination",
        "duration": "1 minute",
        "range": "Self",
        "area_type": "None",
        "dtype": "None",
        "condition": "None",
        "ritual": true,
        "concentration": false,
        "srd": true
    },
    {
        "id": "control-winds",
        "name": "Control Winds",
        "level": "5",
        "school": "Transmutation",
        "duration": "1 hour",
        "range": "300 feet",
        "area_type": "cube (100)",
        "dtype": "None",
        "condition": "Prone",
        "ritual": false,
        "concentration": true,
        "srd": false
    },
    {
        "id": "create-spelljamming-helm",
        "name": "Create Spelljamming Helm",
        "level": "5",
        "school": "Transmutation",
        "duration": "Instantaneous",
        "range": "Touch",
        "area_type": "None",
        "dtype": "None",
        "condition": "None",
        "ritual": false,
        "concentration": false,
        "srd": false
    },
    {
        "id": "creation",
        "name": "Creation",
        "level": "5",
        "school": "Illusion",
        "duration": "Special",
        "range": "30 feet",
        "area_type": "cube (5)",
        "dtype": "None",
        "condition": "None",
        "ritual": false,
        "concentration": false,
        "srd": true
    },
    {
        "id": "danse-macabre",
        "name": "Danse Macabre",
        "level": "5",
        "school": "Necromancy",
        "duration": "1 hour",
        "range": "60 feet",
        "area_type": "None",
        "dtype": "None",
        "condition": "None",
        "ritual": false,
        "concentration": true,
        "srd": false
    },
    {
        "id": "dawn",
        "name": "Dawn",
        "level": "5",
        "school": "Evocation",
        "duration": "1 minute",
        "range": "60 feet",
        "area_type": "cylinder (30)",
        "dtype": "Radiant",
        "condition": "None",
        "ritual": false,
        "concentration": true,
        "srd": false
    },
    {
        "id": "dominate-person",
        "name": "Dominate Person",
        "level": "5",
        "school": "Enchantment",
        "duration": "1 minute",
        "range": "60 feet",
        "area_type": "None",
        "dtype": "None",
        "condition": "Charmed",
        "ritual": false,
        "concentration": true,
        "srd": true
    },
    {
        "id": "dream",
        "name": "Dream",
        "level": "5",
        "school": "Illusion",
        "duration": "Special",
        "range": "10 feet",
        "area_type": "None",
        "dtype": "Psychic",
        "condition": "None",
        "ritual": false,
        "concentration": false,
        "srd": true
    },
    {
        "id": "enervation",
        "name": "Enervation",
        "level": "5",
        "school": "Necromancy",
        "duration": "1 minute",
        "range": "60 feet",
        "area_type": "None",
        "dtype": "Necrotic",
        "condition": "None",
        "ritual": false,
        "concentration": true,
        "srd": false
    },
    {
        "id": "far-step",
        "name": "Far Step",
        "level": "5",
        "school": "Conjuration",
        "duration": "1 minute",
        "range": "Self",
        "area_type": "None",
        "dtype": "None",
        "condition": "None",
        "ritual": false,
        "concentration": true,
        "srd": false
    },
    {
        "id": "geas",
        "name": "Geas",
        "level": "5",
        "school": "Enchantment",
        "duration": "30 days",
        "range": "60 feet",
        "area_type": "None",
        "dtype": "Psychic",
        "condition": "Charmed",
        "ritual": false,
        "concentration": false,
        "srd": true
    },
    {
        "id": "hold-monster",
        "name": "Hold Monster",
        "level": "5",
        "school": "Enchantment",
        "duration": "1 minute",
        "range": "90 feet",
        "area_type": "None",
        "dtype": "None",
        "condition": "Paralyzed",
        "ritual": false,
        "concentration": true,
        "srd": true
    },
    {
        "id": "immolation",
        "name": "Immolation",
        "level": "5",
        "school": "Evocation",
        "duration": "1 minute",
        "range": "90 feet",
        "area_type": "None",
        "dtype": "Fire",
        "condition": "None",
        "ritual": false,
        "concentration": true,
        "srd": false
    },
    {
        "id": "infernal-calling",
        "name": "Infernal Calling",
        "level": "5",
        "school": "Conjuration",
        "duration": "1 hour",
        "range": "90 feet",
        "area_type": "None",
        "dtype": "None",
        "condition": "None",
        "ritual": false,
        "concentration": true,
        "srd": false
    },
    {
        "id": "jallarzis-storm-of-radiance",
        "name": "Jallarzis Storm of Radiance",
        "level": "5",
        "school": "Evocation",
        "duration": "1 minute",
        "range": "120 feet",
        "area_type": "cylinder (10)",
        "dtype": "Multiple",
        "condition": "Multiple",
        "ritual": false,
        "concentration": true,
        "srd": false
    },
    {
        "id": "legend-lore",
        "name": "Legend Lore",
        "level": "5",
        "school": "Divination",
        "duration": "Instantaneous",
        "range": "Self",
        "area_type": "None",
        "dtype": "None",
        "condition": "None",
        "ritual": false,
        "concentration": false,
        "srd": true
    },
    {
        "id": "mislead",
        "name": "Mislead",
        "level": "5",
        "school": "Illusion",
        "duration": "1 hour",
        "range": "Self",
        "area_type": "None",
        "dtype": "None",
        "condition": "Invisible",
        "ritual": false,
        "concentration": true,
        "srd": true
    },
    {
        "id": "modify-memory",
        "name": "Modify Memory",
        "level": "5",
        "school": "Enchantment",
        "duration": "1 minute",
        "range": "30 feet",
        "area_type": "None",
        "dtype": "None",
        "condition": "Charmed",
        "ritual": false,
        "concentration": true,
        "srd": true
    },
    {
        "id": "negative-energy-flood",
        "name": "Negative Energy Flood",
        "level": "5",
        "school": "Necromancy",
        "duration": "Instantaneous",
        "range": "60 feet",
        "area_type": "None",
        "dtype": "Necrotic",
        "condition": "None",
        "ritual": false,
        "concentration": false,
        "srd": false
    },
    {
        "id": "passwall",
        "name": "Passwall",
        "level": "5",
        "school": "Transmutation",
        "duration": "1 hour",
        "range": "30 feet",
        "area_type": "None",
        "dtype": "None",
        "condition": "None",
        "ritual": false,
        "concentration": false,
        "srd": true
    },
    {
        "id": "planar-binding",
        "name": "Planar Binding",
        "level": "5",
        "school": "Abjuration",
        "duration": "24 hours",
        "range": "60 feet",
        "area_type": "None",
        "dtype": "None",
        "condition": "None",
        "ritual": false,
        "concentration": false,
        "srd": true
    },
    {
        "id": "rarys-telepathic-bond",
        "name": "Rarys Telepathic Bond",
        "level": "5",
        "school": "Divination",
        "duration": "1 hour",
        "range": "30 feet",
        "area_type": "None",
        "dtype": "None",
        "condition": "None",
        "ritual": true,
        "concentration": false,
        "srd": true
    },
    {
        "id": "scrying",
        "name": "Scrying",
        "level": "5",
        "school": "Divination",
        "duration": "10 minutes",
        "range": "Self",
        "area_type": "None",
        "dtype": "None",
        "condition": "None",
        "ritual": false,
        "concentration": true,
        "srd": true
    },
    {
        "id": "seeming",
        "name": "Seeming",
        "level": "5",
        "school": "Illusion",
        "duration": "8 hours",
        "range": "30 feet",
        "area_type": "None",
        "dtype": "None",
        "condition": "None",
        "ritual": false,
        "concentration": false,
        "srd": true
    },
    {
        "id": "skill-empowerment",
        "name": "Skill Empowerment",
        "level": "5",
        "school": "Transmutation",
        "duration": "1 hour",
        "range": "Touch",
        "area_type": "None",
        "dtype": "None",
        "condition": "None",
        "ritual": false,
        "concentration": true,
        "srd": false
    },
    {
        "id": "steel-wind-strike",
        "name": "Steel Wind Strike",
        "level": "5",
        "school": "Conjuration",
        "duration": "Instantaneous",
        "range": "30 feet",
        "area_type": "None",
        "dtype": "Force",
        "condition": "None",
        "ritual": false,
        "concentration": false,
        "srd": false
    },
    {
        "id": "summon-draconic-spirit",
        "name": "Summon Draconic Spirit",
        "level": "5",
        "school": "Conjuration",
        "duration": "1 hour",
        "range": "60 feet",
        "area_type": "None",
        "dtype": "None",
        "condition": "None",
        "ritual": false,
        "concentration": true,
        "srd": false
    },
    {
        "id": "summon-dragon",
        "name": "Summon Dragon",
        "level": "5",
        "school": "Conjuration",
        "duration": "1 hour",
        "range": "60 feet",
        "area_type": "None",
        "dtype": "None",
        "condition": "None",
        "ritual": false,
        "concentration": true,
        "srd": false
    },
    {
        "id": "synaptic-static",
        "name": "Synaptic Static",
        "level": "5",
        "school": "Enchantment",
        "duration": "Instantaneous",
        "range": "120 feet",
        "area_type": "sphere (20)",
        "dtype": "Psychic",
        "condition": "None",
        "ritual": false,
        "concentration": false,
        "srd": false
    },
    {
        "id": "telekinesis",
        "name": "Telekinesis",
        "level": "5",
        "school": "Transmutation",
        "duration": "10 minutes",
        "range": "60 feet",
        "area_type": "None",
        "dtype": "None",
        "condition": "Restrained",
        "ritual": false,
        "concentration": true,
        "srd": true
    },
    {
        "id": "teleportation-circle",
        "name": "Teleportation Circle",
        "level": "5",
        "school": "Conjuration",
        "duration": "1 round",
        "range": "10 feet",
        "area_type": "None",
        "dtype": "None",
        "condition": "None",
        "ritual": false,
        "concentration": false,
        "srd": true
    },
    {
        "id": "transmute-rock",
        "name": "Transmute Rock",
        "level": "5",
        "school": "Transmutation",
        "duration": "Until dispelled",
        "range": "120 feet",
        "area_type": "cube (40)",
        "dtype": "Bludgeoning",
        "condition": "Restrained",
        "ritual": false,
        "concentration": false,
        "srd": false
    },
    {
        "id": "wall-of-force",
        "name": "Wall of Force",
        "level": "5",
        "school": "Evocation",
        "duration": "10 minutes",
        "range": "120 feet",
        "area_type": "None",
        "dtype": "None",
        "condition": "Invisible",
        "ritual": false,
        "concentration": true,
        "srd": true
    },
    {
        "id": "wall-of-light",
        "name": "Wall of Light",
        "level": "5",
        "school": "Evocation",
        "duration": "10 minutes",
        "range": "120 feet",
        "area_type": "None",
        "dtype": "Radiant",
        "condition": "Blinded",
        "ritual": false,
        "concentration": true,
        "srd": false
    },
    {
        "id": "wall-of-stone",
        "name": "Wall of Stone",
        "level": "5",
        "school": "Evocation",
        "duration": "10 minutes",
        "range": "120 feet",
        "area_type": "None",
        "dtype": "None",
        "condition": "None",
        "ritual": false,
        "concentration": true,
        "srd": true
    },
    {
        "id": "yolandes-regal-presence",
        "name": "Yolandes Regal Presence",
        "level": "5",
        "school": "Enchantment",
        "duration": "1 minute",
        "range": "Self",
        "area_type": "sphere (10)",
        "dtype": "Psychic",
        "condition": "Prone",
        "ritual": false,
        "concentration": true,
        "srd": false
    }
]